polyra/__init__.py
polyra/basereg.py
polyra/borderspace.py
polyra/halfspace.py
polyra/hitnrun.py
polyra/lp.py
polyra/polyra.py
polyra/rand.py
polyra/region.py
polyra/rfalse.py
polyra/rnot.py
polyra/ror.py
polyra/rtrue.py
polyra/sampler.py
polyra-0.1.dist-info/METADATA
polyra-0.1.dist-info/WHEEL
polyra-0.1.dist-info/top_level.txt
polyra-0.1.dist-info/RECORD
