Metadata-Version: 2.4
Name: polyra
Version: 0.1
Summary: Python module providing tools for Polyra Swarm Learning.
Home-page: https://github.com/psorus/polyra_lib
Download-URL: https://github.com/psorus/polyra_lib/archive/v_01.tar.gz
Author: Simon Klüttermann
Author-email: Simon.Kluettermann@cs.tu-dortmund.de
License: apache-2.0
Keywords: Machine Learning,Polyra,Polyra Swarm,Swarm Learning,ML
Classifier: Development Status :: 3 - Alpha
Classifier: Intended Audience :: Science/Research
Classifier: Topic :: Software Development :: Build Tools
Classifier: License :: OSI Approved :: Apache Software License
Classifier: Programming Language :: Python :: 3
Classifier: Programming Language :: Python :: 3.6
Classifier: Programming Language :: Python :: 3.7
Classifier: Programming Language :: Python :: 3.8
Classifier: Programming Language :: Python :: 3.9
Classifier: Programming Language :: Python :: 3.10
Requires-Dist: numpy
Requires-Dist: tqdm
Dynamic: author
Dynamic: author-email
Dynamic: classifier
Dynamic: download-url
Dynamic: home-page
Dynamic: keywords
Dynamic: license
Dynamic: requires-dist
Dynamic: summary
